{
    "1182": {
        "lat": -37.28629,
        "lon": -72.71243,
        "sensors": {
            "H2S-10": [
                11246,
                1.0
            ],
            "TVOC-P-3": [
                11247,
                1.0
            ],
            "CH3SH": [
                11245,
                1.0
            ]
        }
    },
    "1180": {
        "lat": -37.28989,
        "lon": -72.71081,
        "sensors": {
            "H2S-10": [
                11240,
                1.0
            ],
            "TVOC-P-3": [
                11241,
                1.0
            ],
            "CH3SH": [
                11239,
                1.0
            ]
        }
    },
    "1181": {
        "lat": -37.28977,
        "lon": -72.71219,
        "sensors": {
            "H2S-10": [
                11243,
                1.0
            ],
            "TVOC-P-3": [
                11244,
                1.0
            ],
            "CH3SH": [
                11242,
                1.0
            ]
        }
    },
    "1183": {
        "lat": -37.28478,
        "lon": -72.71493,
        "sensors": {
            "H2S-10": [
                11249,
                1.0
            ],
            "TVOC-P-3": [
                11250,
                1.0
            ],
            "CH3SH": [
                11248,
                1.0
            ]
        }
    },
    "1192": {
        "lat": -37.29042,
        "lon": -72.71054,
        "sensors": {
            "H2S-10": [
                11277,
                1.0
            ],
            "TVOC-P-3": [
                11278,
                1.0
            ],
            "CH3SH": [
                11276,
                1.0
            ]
        }
    },
    "1184": {
        "lat": -37.29131,
        "lon": -72.7102,
        "sensors": {
            "H2S-10": [
                11252,
                1.0
            ],
            "TVOC-P-3": [
                11253,
                1.0
            ],
            "CH3SH": [
                11251,
                1.0
            ]
        }
    },
    "1187": {
        "lat": -37.28977,
        "lon": -72.71371,
        "sensors": {
            "H2S-10": [
                11260,
                1.0
            ],
            "TVOC-P-3": [
                11261,
                1.0
            ],
            "NH3-50": [
                11262,
                1.0
            ]
        }
    },
    "1190": {
        "lat": -37.28881,
        "lon": -72.71422,
        "sensors": {
            "H2S-10": [
                11269,
                1.0
            ],
            "TVOC-P-3": [
                11270,
                1.0
            ],
            "NH3-50": [
                11271,
                1.0
            ]
        }
    },
    "1191": {
        "lat": -37.28638,
        "lon": -72.71493,
        "sensors": {
            "H2S-10": [
                11273,
                1.0
            ],
            "TVOC-P-3": [
                11274,
                1.0
            ],
            "NH3-50": [
                11275,
                1.0
            ],
            "CH3SH": [
                11272,
                1.0
            ]
        }
    },
    "1186": {
        "lat": -37.29168,
        "lon": -72.71176,
        "sensors": {
            "H2S-10": [
                11257,
                1.0
            ],
            "TVOC-P-3": [
                11258,
                1.0
            ],
            "NH3-50": [
                11259,
                1.0
            ]
        }
    },
    "1189": {
        "lat": -37.28938,
        "lon": -72.71419,
        "sensors": {
            "H2S-10": [
                11266,
                1.0
            ],
            "TVOC-P-3": [
                11267,
                1.0
            ],
            "NH3-50": [
                11268,
                1.0
            ]
        }
    },
    "1185": {
        "lat": -37.29019,
        "lon": -72.71242,
        "sensors": {
            "H2S-10": [
                11254,
                1.0
            ],
            "TVOC-P-3": [
                11255,
                1.0
            ],
            "NH3-50": [
                11256,
                1.0
            ]
        }
    },
    "1188": {
        "lat": -37.28934,
        "lon": -72.71369,
        "sensors": {
            "H2S-10": [
                11263,
                1.0
            ],
            "TVOC-P-3": [
                11264,
                1.0
            ],
            "NH3-50": [
                11265,
                1.0
            ]
        }
    }
}